topsis/R102003688.py
topsis/__init__.py
Topsis_Rishab_102003688-0.0.2.dist-info/LICENSE
Topsis_Rishab_102003688-0.0.2.dist-info/METADATA
Topsis_Rishab_102003688-0.0.2.dist-info/WHEEL
Topsis_Rishab_102003688-0.0.2.dist-info/top_level.txt
Topsis_Rishab_102003688-0.0.2.dist-info/RECORD
