Metadata-Version: 2.1
Name: Topsis-Rishab-102003688
Version: 0.0.2
Summary: Topsis package implementation
Home-page: UNKNOWN
Author: Rishab Chakrabarti
Author-email: <rishab.chakrabarti@gmail.com>
License: UNKNOWN
Keywords: python
Platform: UNKNOWN
Classifier: Development Status :: 1 - Planning
Classifier: Intended Audience :: Developers
Classifier: Programming Language :: Python :: 3
Classifier: Operating System :: Unix
Classifier: Operating System :: MacOS :: MacOS X
Classifier: Operating System :: Microsoft :: Windows
License-File: LICENSE
